{
  "meta": {
    "cuts": {
      "oos": "2025-02-24 00:00:00+00:00",
      "lockbox": "2025-12-17 00:00:00+00:00"
    },
    "panel": [
      985,
      56
    ],
    "n_syms_vol": 56,
    "promoted": []
  },
  "rows": [
    {
      "id": "volspike_fade_h1_c1",
      "train": {
        "n": 701,
        "mean": -3.938748437383302e-05,
        "median": 0.018507570977918022,
        "win": 0.5920114122681883,
        "p_pos": 0.5037357906125272,
        "sharpe": -0.00035368757138609083
      },
      "oos": {
        "n": 305,
        "mean": 0.009603648374494957,
        "median": 0.012998372179060216,
        "win": 0.6032786885245902,
        "p_pos": 0.03258610721391807,
        "sharpe": 0.10559142588757686
      },
      "lock": {
        "n": 256,
        "mean": 0.003981221285765615,
        "median": 0.007351975161710569,
        "win": 0.5546875,
        "p_pos": 0.28855816924459066,
        "sharpe": 0.03485011145494786
      },
      "day_oos": {
        "n": 161,
        "mean": 0.013483861497990874,
        "median": 0.01367701547701541,
        "win": 0.5900621118012422,
        "p_pos": 0.009766696730382525,
        "sharpe": 0.1840389106937699
      },
      "v_oos": {
        "verdict": "NOT_PROVEN",
        "reason": "OOS mean +0.9604% n=305 but p_adj=0.261 (trials=8)",
        "p_adj": 0.26068885771134453
      },
      "v_lock": {
        "verdict": "NOT_PROVEN",
        "reason": "OOS mean +0.3981% n=256 but p_adj=0.289 (trials=1)",
        "p_adj": 0.28855816924459066
      },
      "promotion": "NO"
    },
    {
      "id": "volspike_fade_h1_c2",
      "train": {
        "n": 701,
        "mean": -0.0018393874843738293,
        "median": 0.016707570977918022,
        "win": 0.5863052781740371,
        "p_pos": 0.6690583279794533,
        "sharpe": -0.016517137423946636
      },
      "oos": {
        "n": 305,
        "mean": 0.007803648374494959,
        "median": 0.011198372179060216,
        "win": 0.5967213114754099,
        "p_pos": 0.06700919040991633,
        "sharpe": 0.08580055483669528
      },
      "lock": {
        "n": 256,
        "mean": 0.0021812212857656235,
        "median": 0.005551975161710568,
        "win": 0.546875,
        "p_pos": 0.37999366279310187,
        "sharpe": 0.019093589494415232
      },
      "day_oos": {
        "n": 161,
        "mean": 0.011683861497990876,
        "median": 0.011877015477015411,
        "win": 0.577639751552795,
        "p_pos": 0.02151285123375713,
        "sharpe": 0.15947101971549596
      },
      "v_oos": {
        "verdict": "NOT_PROVEN",
        "reason": "OOS mean +0.7804% n=305 but p_adj=0.536 (trials=8)",
        "p_adj": 0.5360735232793307
      },
      "v_lock": {
        "verdict": "NOT_PROVEN",
        "reason": "OOS mean +0.2181% n=256 but p_adj=0.380 (trials=1)",
        "p_adj": 0.37999366279310187
      }
    },
    {
      "id": "volspike_fade_h2_c1",
      "train": {
        "n": 701,
        "mean": -0.0099424826677696,
        "median": 0.012511270125223708,
        "win": 0.5663338088445078,
        "p_pos": 0.9564058466957286,
        "sharpe": -0.06460165722631067
      },
      "oos": {
        "n": 305,
        "mean": 0.030437794206024403,
        "median": 0.032195273827785,
        "win": 0.6295081967213115,
        "p_pos": 4.20416705239472e-07,
        "sharpe": 0.2820415044282493
      },
      "lock": {
        "n": 256,
        "mean": 0.006626050863365813,
        "median": 0.016617301536993558,
        "win": 0.578125,
        "p_pos": 0.23253177231534278,
        "sharpe": 0.0456584050242586
      },
      "day_oos": {
        "n": 161,
        "mean": 0.02031201197783745,
        "median": 0.01654997417274849,
        "win": 0.5838509316770186,
        "p_pos": 0.002593918567826253,
        "sharpe": 0.2202873385120656
      },
      "v_oos": {
        "verdict": "NOT_PROVEN",
        "reason": "OOS ok but train mean -0.9942% \u2264 0 (inconsistent)",
        "p_adj": 3.363333641915776e-06
      },
      "v_lock": {
        "verdict": "NOT_PROVEN",
        "reason": "OOS mean +0.6626% n=256 but p_adj=0.233 (trials=1)",
        "p_adj": 0.23253177231534278
      },
      "promotion": "NO"
    },
    {
      "id": "volspike_fade_h2_c2",
      "train": {
        "n": 701,
        "mean": -0.011742482667769593,
        "median": 0.010711270125223708,
        "win": 0.5592011412268189,
        "p_pos": 0.9783122582700228,
        "sharpe": -0.07629722531458219
      },
      "oos": {
        "n": 305,
        "mean": 0.028637794206024404,
        "median": 0.030395273827785,
        "win": 0.6262295081967213,
        "p_pos": 1.7902576031851886e-06,
        "sharpe": 0.26536241446087033
      },
      "lock": {
        "n": 256,
        "mean": 0.004826050863365817,
        "median": 0.014817301536993559,
        "win": 0.5625,
        "p_pos": 0.29733490677086327,
        "sharpe": 0.03325506995509223
      },
      "day_oos": {
        "n": 161,
        "mean": 0.018512011977837455,
        "median": 0.01474997417274849,
        "win": 0.577639751552795,
        "p_pos": 0.0054258996170951914,
        "sharpe": 0.20076602227050572
      },
      "v_oos": {
        "verdict": "NOT_PROVEN",
        "reason": "OOS ok but train mean -1.1742% \u2264 0 (inconsistent)",
        "p_adj": 1.4322060825481509e-05
      },
      "v_lock": {
        "verdict": "NOT_PROVEN",
        "reason": "OOS mean +0.4826% n=256 but p_adj=0.297 (trials=1)",
        "p_adj": 0.29733490677086327
      }
    },
    {
      "id": "volspike_fade_h3_c1",
      "train": {
        "n": 701,
        "mean": -0.002433139464783724,
        "median": 0.021686430062630515,
        "win": 0.5748930099857347,
        "p_pos": 0.6303450370544255,
        "sharpe": -0.012568448346385772
      },
      "oos": {
        "n": 305,
        "mean": 0.04098165925344322,
        "median": 0.04165238095238102,
        "win": 0.6229508196721312,
        "p_pos": 4.544804316231981e-08,
        "sharpe": 0.30599900108267225
      },
      "lock": {
        "n": 256,
        "mean": 0.010511671041436224,
        "median": 0.027889719511352353,
        "win": 0.62109375,
        "p_pos": 0.149497279715646,
        "sharpe": 0.0649119957759844
      },
      "day_oos": {
        "n": 161,
        "mean": 0.020992764725123476,
        "median": 0.024127106577409376,
        "win": 0.577639751552795,
        "p_pos": 0.004314530717217501,
        "sharpe": 0.20699016561341688
      },
      "v_oos": {
        "verdict": "NOT_PROVEN",
        "reason": "OOS ok but train mean -0.2433% \u2264 0 (inconsistent)",
        "p_adj": 3.635843452985585e-07
      },
      "v_lock": {
        "verdict": "NOT_PROVEN",
        "reason": "OOS mean +1.0512% n=256 but p_adj=0.149 (trials=1)",
        "p_adj": 0.149497279715646
      },
      "promotion": "NO"
    },
    {
      "id": "volspike_fade_h3_c2",
      "train": {
        "n": 701,
        "mean": -0.004233139464783723,
        "median": 0.019886430062630515,
        "win": 0.572039942938659,
        "p_pos": 0.7186863807739909,
        "sharpe": -0.021866397498472415
      },
      "oos": {
        "n": 305,
        "mean": 0.039181659253443225,
        "median": 0.03985238095238102,
        "win": 0.6229508196721312,
        "p_pos": 1.616590660371636e-07,
        "sharpe": 0.29255888635860744
      },
      "lock": {
        "n": 256,
        "mean": 0.00871167104143623,
        "median": 0.026089719511352354,
        "win": 0.60546875,
        "p_pos": 0.19468917359326535,
        "sharpe": 0.05379658016449972
      },
      "day_oos": {
        "n": 161,
        "mean": 0.01919276472512348,
        "median": 0.022327106577409377,
        "win": 0.577639751552795,
        "p_pos": 0.00817042751595134,
        "sharpe": 0.18924203653262672
      },
      "v_oos": {
        "verdict": "NOT_PROVEN",
        "reason": "OOS ok but train mean -0.4233% \u2264 0 (inconsistent)",
        "p_adj": 1.2932725282973088e-06
      },
      "v_lock": {
        "verdict": "NOT_PROVEN",
        "reason": "OOS mean +0.8712% n=256 but p_adj=0.195 (trials=1)",
        "p_adj": 0.19468917359326535
      }
    },
    {
      "id": "volspike_fade_h5_c1",
      "train": {
        "n": 701,
        "mean": -0.027448517859825137,
        "median": 0.017087262079062995,
        "win": 0.5520684736091298,
        "p_pos": 0.9960107266906382,
        "sharpe": -0.10020153297542299
      },
      "oos": {
        "n": 305,
        "mean": 0.03093063798461227,
        "median": 0.051042809364548435,
        "win": 0.6557377049180327,
        "p_pos": 0.000149187589981124,
        "sharpe": 0.20709201761258703
      },
      "lock": {
        "n": 253,
        "mean": 0.01604707465343241,
        "median": 0.027232258064516148,
        "win": 0.5968379446640316,
        "p_pos": 0.08444357980814853,
        "sharpe": 0.08649507445835253
      },
      "day_oos": {
        "n": 161,
        "mean": 0.021173921024666975,
        "median": 0.02653530106257376,
        "win": 0.6024844720496895,
        "p_pos": 0.02947419482401355,
        "sharpe": 0.1488408019125754
      },
      "v_oos": {
        "verdict": "NOT_PROVEN",
        "reason": "OOS ok but train mean -2.7449% \u2264 0 (inconsistent)",
        "p_adj": 0.001193500719848992
      },
      "v_lock": {
        "verdict": "NOT_PROVEN",
        "reason": "OOS mean +1.6047% n=253 but p_adj=0.084 (trials=1)",
        "p_adj": 0.08444357980814853
      },
      "promotion": "NO"
    },
    {
      "id": "volspike_fade_h5_c2",
      "train": {
        "n": 701,
        "mean": -0.029248517859825133,
        "median": 0.015287262079062995,
        "win": 0.5492154065620543,
        "p_pos": 0.9976503268986504,
        "sharpe": -0.10677248009456591
      },
      "oos": {
        "n": 305,
        "mean": 0.02913063798461227,
        "median": 0.04924280936454844,
        "win": 0.6557377049180327,
        "p_pos": 0.0003293292776494114,
        "sharpe": 0.1950403544077057
      },
      "lock": {
        "n": 253,
        "mean": 0.014247074653432413,
        "median": 0.02543225806451615,
        "win": 0.5928853754940712,
        "p_pos": 0.11095477214579083,
        "sharpe": 0.07679292391767858
      },
      "day_oos": {
        "n": 161,
        "mean": 0.01937392102466698,
        "median": 0.02473530106257376,
        "win": 0.6024844720496895,
        "p_pos": 0.04199145956248863,
        "sharpe": 0.13618781037971173
      },
      "v_oos": {
        "verdict": "NOT_PROVEN",
        "reason": "OOS ok but train mean -2.9249% \u2264 0 (inconsistent)",
        "p_adj": 0.002634634221195291
      },
      "v_lock": {
        "verdict": "NOT_PROVEN",
        "reason": "OOS mean +1.4247% n=253 but p_adj=0.111 (trials=1)",
        "p_adj": 0.11095477214579083
      }
    },
    {
      "id": "volspike_tight_h2",
      "train": {
        "n": 312,
        "mean": -0.023136057340431223,
        "median": 0.009498094911514678,
        "win": 0.5544871794871795,
        "p_pos": 0.9869267276004101,
        "sharpe": -0.12591080454488643
      },
      "oos": {
        "n": 135,
        "mean": 0.029512128117922386,
        "median": 0.03636793893129777,
        "win": 0.6592592592592592,
        "p_pos": 0.00043727144214531145,
        "sharpe": 0.2864334537976454
      },
      "lock": {
        "n": 146,
        "mean": 0.008343721284950133,
        "median": 0.016229325513563788,
        "win": 0.5684931506849316,
        "p_pos": 0.26697361171777834,
        "sharpe": 0.05147641222880572
      },
      "day_oos": {
        "n": 107,
        "mean": 0.02531626070561947,
        "median": 0.02678616271926229,
        "win": 0.6355140186915887,
        "p_pos": 0.005196061005813637,
        "sharpe": 0.24772634404051602
      },
      "v_oos": {
        "verdict": "NOT_PROVEN",
        "reason": "OOS ok but train mean -2.3136% \u2264 0 (inconsistent)",
        "p_adj": 0.0017490857685812458
      }
    },
    {
      "id": "volspike_tight_h3",
      "train": {
        "n": 312,
        "mean": -0.02559014147493702,
        "median": 0.010537352470514707,
        "win": 0.5384615384615384,
        "p_pos": 0.9847040966680447,
        "sharpe": -0.12241852253152284
      },
      "oos": {
        "n": 135,
        "mean": 0.03137995762959277,
        "median": 0.041075157629255975,
        "win": 0.6370370370370371,
        "p_pos": 0.0022441168410254194,
        "sharpe": 0.2445693112801788
      },
      "lock": {
        "n": 146,
        "mean": 0.0224502186257945,
        "median": 0.03394599794257249,
        "win": 0.636986301369863,
        "p_pos": 0.03270966742385688,
        "sharpe": 0.15247659544287598
      },
      "day_oos": {
        "n": 107,
        "mean": 0.026595758563634813,
        "median": 0.04366226737044995,
        "win": 0.6355140186915887,
        "p_pos": 0.01101474993651005,
        "sharpe": 0.22136901128616093
      },
      "v_oos": {
        "verdict": "NOT_PROVEN",
        "reason": "OOS ok but train mean -2.5590% \u2264 0 (inconsistent)",
        "p_adj": 0.008976467364101678
      }
    },
    {
      "id": "volspike_follow_h3_control",
      "train": {
        "n": 701,
        "mean": -0.00116686053521629,
        "median": -0.025286430062630514,
        "win": 0.41512125534950073,
        "p_pos": 0.5633960823461125,
        "sharpe": -0.006027449957787597
      },
      "oos": {
        "n": 305,
        "mean": -0.04458165925344323,
        "median": -0.04525238095238102,
        "win": 0.3639344262295082,
        "p_pos": 0.9999999969407425,
        "sharpe": -0.332879230530802
      },
      "lock": {
        "n": 256,
        "mean": -0.014111671041436239,
        "median": -0.031489719511352356,
        "win": 0.36328125,
        "p_pos": 0.9183842556531752,
        "sharpe": -0.08714282699895391
      },
      "v_oos": {
        "verdict": "REJECTED",
        "reason": "OOS mean -4.4582% \u2264 0 n=305",
        "p_adj": 0.9999999969407425
      }
    }
  ]
}